{
    "id": "id_19fcc5cefb",
    "title": "2025/12/25",
    "content_lines": [
        "今天算是圣诞节吧，关于这些节日什么的我也不是很懂",
        "反正对于学生来说，不放假的节日就不是好节日",
        "大课间跑完早操，老师给我们说有圣诞节活动",
        "活动部的同学在教室的各个角落里藏了可以兑换礼品的卡片",
        "我刚上楼就找到一张",
        "打开来一看居然TM是“Merry  Christmas”",
        "得",
        "啥都没有",
        "",
        "",
        "------假装是分割线-------",
        "晚自习",
        "班主任老师突然给守晚自习的老师打电话",
        "让我这个管班上电子设备的人去手机柜看看",
        "有没有一部华为的小折叠",
        "跟nm规则怪谈一样",
        "给我(*Φ皿Φ*)吓得半死",
        "",
        "-----假装是分割线--------",
        "哎",
        "大课间的时候又看见__了",
        "不说了",
        "就这样吧",
        "给张大香蕉生成的诗岸ciallow图吧",
        "--- 发布时间：2025-12-25 21:29:01 ---"
    ],
    "images": [
        {
            "name": "img4.png",
            "insert_after": 23
        }
    ],
    "date": "2025-12-25 21:29:01"
}